{"timestamp": 1771594753.8836708, "value": {"ticker": "BNBX", "company_name": "BNB Plus Corp.", "short_name": "BNB Plus Corp.", "sector": "Financial Services", "industry": "Asset Management", "country": "United States", "market_cap": 4275173, "float_shares": 5349578, "shares_outstanding": 5447469, "short_ratio": 0.27, "short_percent_of_float": 0.0168, "shares_short": 70846, "shares_short_prior": 200588, "insider_percent_held": 0.07935, "institution_percent_held": 0.01977, "total_cash": 2450536, "total_debt": 48861, "total_revenue": 1832038, "revenue_growth": -0.35, "earnings_growth": 0, "profit_margins": 0.0, "gross_margins": 0.29913, "operating_margins": -32.48758, "debt_to_equity": 0.265, "current_ratio": 2.318, "book_value": 3.947, "price_to_book": 0.19883455, "operating_cashflow": -14737745, "free_cashflow": -17404216, "price": 0.7848, "52w_high": 127.5, "52w_low": 0.7235, "avg_volume": 133173, "avg_volume_10d": 111640, "full_time_employees": 26, "audit_risk": 0, "overall_risk": 0}}