{"timestamp": 1771603368.048537, "value": {"ticker": "FRGT", "company_name": "Freight Technologies, Inc.", "short_name": "Freight Technologies, Inc.", "sector": "Technology", "industry": "Software - Application", "country": "Mexico", "market_cap": 1845811, "float_shares": 1388582, "shares_outstanding": 1564246, "short_ratio": 0.2, "short_percent_of_float": 0.074499995, "shares_short": 115701, "shares_short_prior": 37023, "insider_percent_held": 0.075780004, "institution_percent_held": 0.12145001, "total_cash": 291940, "total_debt": 3314656, "total_revenue": 13263031, "revenue_growth": 0.302, "earnings_growth": 0, "profit_margins": -0.40286, "gross_margins": -0.24430999, "operating_margins": -0.54327, "debt_to_equity": 52.747, "current_ratio": 0.945, "book_value": 0.304, "price_to_book": 3.881579, "operating_cashflow": -5455359, "free_cashflow": 0, "price": 1.18, "52w_high": 69.8, "52w_low": 1.05, "avg_volume": 1272318, "avg_volume_10d": 279900, "full_time_employees": 82, "audit_risk": 0, "overall_risk": 0}}