{"timestamp": 1771603066.2942932, "value": {"ticker": "BBAI", "company_name": "BigBear.ai Holdings, Inc.", "short_name": "BigBear.ai, Inc.", "sector": "Technology", "industry": "Information Technology Services", "country": "United States", "market_cap": 1897966080, "float_shares": 433333845, "shares_outstanding": 457892893, "short_ratio": 1.51, "short_percent_of_float": 0.265, "shares_short": 120746980, "shares_short_prior": 107434715, "insider_percent_held": 0.00614, "institution_percent_held": 0.48098, "total_cash": 586664000, "total_debt": 112890000, "total_revenue": 144199008, "revenue_growth": -0.201, "earnings_growth": 0, "profit_margins": -2.95609, "gross_margins": 0.27278, "operating_margins": -0.53348, "debt_to_equity": 18.506, "current_ratio": 3.131, "book_value": 1.4, "price_to_book": 2.9607143, "operating_cashflow": -34923000, "free_cashflow": 141600128, "price": 4.145, "52w_high": 9.45, "52w_low": 2.36, "avg_volume": 86313398, "avg_volume_10d": 60033800, "full_time_employees": 630, "audit_risk": 10, "overall_risk": 9}}