{"timestamp": 1771594763.7729642, "value": {"ticker": "EDSA", "company_name": "Edesa Biotech, Inc.", "short_name": "Edesa Biotech, Inc.", "sector": "Healthcare", "industry": "Biotechnology", "country": "Canada", "market_cap": 7537554, "float_shares": 4748768, "shares_outstanding": 8348161, "short_ratio": 0.47, "short_percent_of_float": 0.0039, "shares_short": 28454, "shares_short_prior": 27859, "insider_percent_held": 0.17031999, "institution_percent_held": 0.36567003, "total_cash": 12051748, "total_debt": 0, "total_revenue": 0, "revenue_growth": 0, "earnings_growth": 0, "profit_margins": 0.0, "gross_margins": 0.0, "operating_margins": 0.0, "debt_to_equity": 0, "current_ratio": 16.818, "book_value": 0.559, "price_to_book": 1.6152056, "operating_cashflow": -7892393, "free_cashflow": -5372837, "price": 0.9029, "52w_high": 2.95, "52w_low": 0.8921, "avg_volume": 63193, "avg_volume_10d": 142320, "full_time_employees": 17, "audit_risk": 0, "overall_risk": 0}}