{"timestamp": 1774982105.0794327, "value": {"ticker": "IOVA", "company_name": "Iovance Biotherapeutics, Inc.", "short_name": "Iovance Biotherapeutics, Inc.", "sector": "Healthcare", "industry": "Biotechnology", "country": "United States", "market_cap": 1462463616, "float_shares": 353409504, "shares_outstanding": 411961607, "short_ratio": 5.24, "short_percent_of_float": 0.3005, "shares_short": 115070206, "shares_short_prior": 131334639, "insider_percent_held": 0.00402, "institution_percent_held": 0.71089995, "total_cash": 296980000, "total_debt": 49444000, "total_revenue": 263502000, "revenue_growth": 0.177, "earnings_growth": 0, "profit_margins": -1.48378, "gross_margins": 0.34276, "operating_margins": -0.84660006, "debt_to_equity": 7.078, "current_ratio": 3.2, "book_value": 1.696, "price_to_book": 2.0931604, "operating_cashflow": -302408000, "free_cashflow": -162422128, "price": 3.55, "52w_high": 5.63, "52w_low": 1.64, "avg_volume": 15205931, "avg_volume_10d": 11551900, "full_time_employees": 975, "audit_risk": 8, "overall_risk": 6}}