{"timestamp": 1775482419.642903, "value": {"ticker": "POWW", "company_name": "Outdoor Holding Company", "short_name": "Outdoor Holding Company", "sector": "Industrials", "industry": "Aerospace & Defense", "country": "United States", "market_cap": 240441872, "float_shares": 87518499, "shares_outstanding": 117288722, "short_ratio": 3.42, "short_percent_of_float": 0.028199999, "shares_short": 2746964, "shares_short_prior": 3461869, "insider_percent_held": 0.10658, "institution_percent_held": 0.52044, "total_cash": 69857728, "total_debt": 11237441, "total_revenue": 46019480, "revenue_growth": 0.532, "earnings_growth": 0, "profit_margins": -0.32002997, "gross_margins": 0.95389, "operating_margins": 0.14706, "debt_to_equity": 4.736, "current_ratio": 3.996, "book_value": 2.023, "price_to_book": 1.0133464, "operating_cashflow": -736715, "free_cashflow": 28814882, "price": 2.05, "52w_high": 2.23, "52w_low": 1.08, "avg_volume": 621266, "avg_volume_10d": 614410, "full_time_employees": 81, "audit_risk": 10, "overall_risk": 10}}