{"timestamp": 1776434936.0051441, "value": {"ticker": "RCKT", "company_name": "Rocket Pharmaceuticals, Inc.", "short_name": "Rocket Pharmaceuticals, Inc.", "sector": "Healthcare", "industry": "Biotechnology", "country": "United States", "market_cap": 432672064, "float_shares": 87075710, "shares_outstanding": 109122837, "short_ratio": 3.64, "short_percent_of_float": 0.20899999, "shares_short": 18580923, "shares_short_prior": 13986075, "insider_percent_held": 0.029749999, "institution_percent_held": 0.84559, "total_cash": 188928992, "total_debt": 24877000, "total_revenue": 0, "revenue_growth": 0, "earnings_growth": 0, "profit_margins": 0.0, "gross_margins": 0.0, "operating_margins": 0.0, "debt_to_equity": 8.974, "current_ratio": 6.381, "book_value": 2.559, "price_to_book": 1.5494334, "operating_cashflow": -190014000, "free_cashflow": -104854376, "price": 3.965, "52w_high": 8.26, "52w_low": 2.19, "avg_volume": 3396067, "avg_volume_10d": 2523810, "full_time_employees": 202, "audit_risk": 8, "overall_risk": 8}}