{"timestamp": 1771603807.307505, "value": {"ticker": "PDSB", "company_name": "PDS Biotechnology Corporation", "short_name": "PDS Biotechnology Corporation", "sector": "Healthcare", "industry": "Biotechnology", "country": "United States", "market_cap": 37270684, "float_shares": 45179925, "shares_outstanding": 54721307, "short_ratio": 2.58, "short_percent_of_float": 0.041100003, "shares_short": 2189274, "shares_short_prior": 1343277, "insider_percent_held": 0.02695, "institution_percent_held": 0.15147, "total_cash": 26198652, "total_debt": 17966972, "total_revenue": 0, "revenue_growth": 0, "earnings_growth": 0, "profit_margins": 0.0, "gross_margins": 0.0, "operating_margins": 0.0, "debt_to_equity": 190.056, "current_ratio": 2.093, "book_value": 0.198, "price_to_book": 3.439899, "operating_cashflow": -32283866, "free_cashflow": -15312097, "price": 0.6811, "52w_high": 2.2, "52w_low": 0.66, "avg_volume": 670911, "avg_volume_10d": 576450, "full_time_employees": 24, "audit_risk": 0, "overall_risk": 0}}