{"timestamp": 1775482030.2856064, "value": {"ticker": "FOSL", "company_name": "Fossil Group, Inc.", "short_name": "Fossil Group, Inc.", "sector": "Consumer Cyclical", "industry": "Footwear & Accessories", "country": "United States", "market_cap": 271352928, "float_shares": 46214252, "shares_outstanding": 58355464, "short_ratio": 3.79, "short_percent_of_float": 0.060300004, "shares_short": 3424481, "shares_short_prior": 5988837, "insider_percent_held": 0.0943, "institution_percent_held": 0.5698, "total_cash": 102224000, "total_debt": 317041984, "total_revenue": 1004406016, "revenue_growth": -0.18, "earnings_growth": 0, "profit_margins": -0.07796, "gross_margins": 0.56068003, "operating_margins": 0.04464, "debt_to_equity": 365.357, "current_ratio": 1.55, "book_value": 1.841, "price_to_book": 2.5258012, "operating_cashflow": -57897000, "free_cashflow": 53871624, "price": 4.65, "52w_high": 5.0, "52w_low": 0.86, "avg_volume": 715928, "avg_volume_10d": 519650, "full_time_employees": 4500, "audit_risk": 3, "overall_risk": 1}}