{"timestamp": 1776438455.872899, "value": {"ticker": "BLZE", "company_name": "Backblaze, Inc.", "short_name": "Backblaze, Inc.", "sector": "Technology", "industry": "Software - Infrastructure", "country": "United States", "market_cap": 245208000, "float_shares": 54657344, "shares_outstanding": 60014731, "short_ratio": 2.43, "short_percent_of_float": 0.0317, "shares_short": 1826647, "shares_short_prior": 1466622, "insider_percent_held": 0.04764, "institution_percent_held": 0.53973997, "total_cash": 51381000, "total_debt": 61584000, "total_revenue": 145835008, "revenue_growth": 0.118, "earnings_growth": 0, "profit_margins": -0.17562, "gross_margins": 0.60965, "operating_margins": -0.04362, "debt_to_equity": 74.001, "current_ratio": 1.066, "book_value": 1.418, "price_to_book": 2.877292, "operating_cashflow": 23544000, "free_cashflow": 23042624, "price": 4.08, "52w_high": 10.858, "52w_low": 3.261, "avg_volume": 824467, "avg_volume_10d": 533310, "full_time_employees": 320, "audit_risk": 8, "overall_risk": 9}}