{"timestamp": 1773165255.5401766, "value": {"ticker": "MBRX", "company_name": "Moleculin Biotech, Inc.", "short_name": "Moleculin Biotech, Inc.", "sector": "Healthcare", "industry": "Biotechnology", "country": "United States", "market_cap": 6281627, "float_shares": 2018112, "shares_outstanding": 3079229, "short_ratio": 4.3, "short_percent_of_float": 0.1454, "shares_short": 441371, "shares_short_prior": 358088, "insider_percent_held": 0.01663, "institution_percent_held": 0.05905, "total_cash": 6703000, "total_debt": 390000, "total_revenue": 0, "revenue_growth": 0, "earnings_growth": 0, "profit_margins": 0.0, "gross_margins": 0.0, "operating_margins": 0.0, "debt_to_equity": 0, "current_ratio": 1.388, "book_value": -13.596, "price_to_book": -0.15004413, "operating_cashflow": -22452000, "free_cashflow": -12177125, "price": 2.04, "52w_high": 33.0, "52w_low": 1.79, "avg_volume": 289272, "avg_volume_10d": 172680, "full_time_employees": 17, "audit_risk": 0, "overall_risk": 0}}