{"timestamp": 1771602771.5344741, "value": {"ticker": "NEOV", "company_name": "NeoVolta Inc.", "short_name": "NeoVolta Inc.", "sector": "Industrials", "industry": "Electrical Equipment & Parts", "country": "United States", "market_cap": 159241440, "float_shares": 35851889, "shares_outstanding": 42577923, "short_ratio": 1.75, "short_percent_of_float": 0.074099995, "shares_short": 2308581, "shares_short_prior": 1756862, "insider_percent_held": 0.11553001, "institution_percent_held": 0.24179001, "total_cash": 242434, "total_debt": 4363168, "total_revenue": 18060792, "revenue_growth": 3.335, "earnings_growth": 0, "profit_margins": -0.5471, "gross_margins": 0.19045, "operating_margins": -0.96362, "debt_to_equity": 87.217, "current_ratio": 2.099, "book_value": 0.138, "price_to_book": 27.10145, "operating_cashflow": -7552491, "free_cashflow": -3919638, "price": 3.74, "52w_high": 7.13, "52w_low": 1.8, "avg_volume": 689635, "avg_volume_10d": 645730, "full_time_employees": 17, "audit_risk": 0, "overall_risk": 0}}