{"timestamp": 1771603778.9817474, "value": {"ticker": "OLOX", "company_name": "Olenox Industries Inc.", "short_name": "Olenox Industries Inc.", "sector": "Industrials", "industry": "Metal Fabrication", "country": "United States", "market_cap": 5707621, "float_shares": 5393839, "shares_outstanding": 6181761, "short_ratio": 0.52, "short_percent_of_float": 0.066700004, "shares_short": 391114, "shares_short_prior": 518574, "insider_percent_held": 0.05341, "institution_percent_held": 0.02484, "total_cash": 3021757, "total_debt": 12194025, "total_revenue": 3382896, "revenue_growth": -0.4, "earnings_growth": 0, "profit_margins": 0.0, "gross_margins": -0.63437, "operating_margins": -2.38566, "debt_to_equity": 48.902, "current_ratio": 0.183, "book_value": 27.544, "price_to_book": 0.03352091, "operating_cashflow": -4800834, "free_cashflow": 1460190, "price": 0.9233, "52w_high": 96.0, "52w_low": 0.85, "avg_volume": 5329698, "avg_volume_10d": 316340, "full_time_employees": 31, "audit_risk": 0, "overall_risk": 0}}