{"timestamp": 1773165291.4576592, "value": {"ticker": "ORGO", "company_name": "Organogenesis Holdings Inc.", "short_name": "Organogenesis Holdings Inc.", "sector": "Healthcare", "industry": "Drug Manufacturers - Specialty & Generic", "country": "United States", "market_cap": 353118624, "float_shares": 58176457, "shares_outstanding": 128640671, "short_ratio": 21.41, "short_percent_of_float": 0.29930001, "shares_short": 13072172, "shares_short_prior": 12892111, "insider_percent_held": 0.4761, "institution_percent_held": 0.54188, "total_cash": 95923000, "total_debt": 82137000, "total_revenue": 564169024, "revenue_growth": 0.781, "earnings_growth": 5.552, "profit_margins": 0.06564, "gross_margins": 0.75624, "operating_margins": 0.28913, "debt_to_equity": 18.929, "current_ratio": 3.617, "book_value": 2.364, "price_to_book": 1.1611674, "operating_cashflow": -10309000, "free_cashflow": -50102376, "price": 2.745, "52w_high": 7.077, "52w_low": 2.61, "avg_volume": 988377, "avg_volume_10d": 985710, "full_time_employees": 854, "audit_risk": 9, "overall_risk": 6}}