{"timestamp": 1771604695.703152, "value": {"ticker": "AMOD", "company_name": "Alpha Modus Holdings, Inc.", "short_name": "Alpha Modus Holdings, Inc.", "sector": "Technology", "industry": "Software - Application", "country": "United States", "market_cap": 23241910, "float_shares": 13983995, "shares_outstanding": 47442151, "short_ratio": 0.18, "short_percent_of_float": 0.0608, "shares_short": 951056, "shares_short_prior": 252465, "insider_percent_held": 0.67010003, "institution_percent_held": 0.04978, "total_cash": 75705, "total_debt": 5326876, "total_revenue": 0, "revenue_growth": 0, "earnings_growth": 0, "profit_margins": 0.0, "gross_margins": 0.0, "operating_margins": 0.0, "debt_to_equity": 0, "current_ratio": 0.037, "book_value": -1.229, "price_to_book": -0.39861676, "operating_cashflow": -3190346, "free_cashflow": 1190854, "price": 0.4899, "52w_high": 3.282, "52w_low": 0.4, "avg_volume": 2353046, "avg_volume_10d": 931900, "full_time_employees": 4, "audit_risk": 0, "overall_risk": 0}}