{"timestamp": 1771600249.5798512, "value": {"ticker": "ZNB", "company_name": "Zeta Network Group", "short_name": "Zeta Network Group", "sector": "Communication Services", "industry": "Entertainment", "country": "China", "market_cap": 38243492, "float_shares": 145644792, "shares_outstanding": 151279166, "short_ratio": 0.89, "short_percent_of_float": 0.0093, "shares_short": 1412949, "shares_short_prior": 1473102, "insider_percent_held": 0.0051599997, "institution_percent_held": 0.00606, "total_cash": 1060893, "total_debt": 4534070, "total_revenue": 8726016, "revenue_growth": 3.93, "earnings_growth": 0, "profit_margins": 0.0, "gross_margins": -0.02859, "operating_margins": -0.17274, "debt_to_equity": 19.441, "current_ratio": 0.298, "book_value": 21.272, "price_to_book": 0.011884167, "operating_cashflow": -8337201, "free_cashflow": 17865152, "price": 0.2528, "52w_high": 33.0, "52w_low": 0.21, "avg_volume": 1550025, "avg_volume_10d": 3003400, "full_time_employees": 14, "audit_risk": 0, "overall_risk": 0}}