{"timestamp": 1773165308.7974646, "value": {"ticker": "PSHG", "company_name": "Performance Shipping Inc.", "short_name": "Performance Shipping Inc.", "sector": "Industrials", "industry": "Marine Shipping", "country": "Greece", "market_cap": 27972356, "float_shares": 11397554, "shares_outstanding": 12432158, "short_ratio": 7.47, "short_percent_of_float": 0.0387, "shares_short": 480690, "shares_short_prior": 559676, "insider_percent_held": 0.0, "institution_percent_held": 0.05429, "total_cash": 49261000, "total_debt": 222332000, "total_revenue": 84172000, "revenue_growth": 0.207, "earnings_growth": -0.226, "profit_margins": 0.5937, "gross_margins": 0.68177, "operating_margins": 0.38856, "debt_to_equity": 68.741, "current_ratio": 0, "book_value": 26.016, "price_to_book": 0.08648524, "operating_cashflow": 0, "free_cashflow": 0, "price": 2.25, "52w_high": 2.58, "52w_low": 1.31, "avg_volume": 116086, "avg_volume_10d": 305910, "full_time_employees": 0, "audit_risk": 0, "overall_risk": 0}}