{"timestamp": 1773165190.919793, "value": {"ticker": "EDIT", "company_name": "Editas Medicine, Inc.", "short_name": "Editas Medicine, Inc.", "sector": "Healthcare", "industry": "Biotechnology", "country": "United States", "market_cap": 261081088, "float_shares": 97264304, "shares_outstanding": 97618660, "short_ratio": 6.79, "short_percent_of_float": 0.12060001, "shares_short": 11747144, "shares_short_prior": 11829004, "insider_percent_held": 0.0026800002, "institution_percent_held": 0.54471, "total_cash": 165648000, "total_debt": 19652000, "total_revenue": 40520000, "revenue_growth": -0.192, "earnings_growth": 0, "profit_margins": 0.0, "gross_margins": -1.21997, "operating_margins": -0.56651, "debt_to_equity": 146.079, "current_ratio": 0, "book_value": 0.144, "price_to_book": 18.572918, "operating_cashflow": 0, "free_cashflow": 0, "price": 2.6745, "52w_high": 4.537, "52w_low": 0.91, "avg_volume": 1830274, "avg_volume_10d": 2307850, "full_time_employees": 0, "audit_risk": 5, "overall_risk": 9}}