{"timestamp": 1771594755.296075, "value": {"ticker": "BZFD", "company_name": "BuzzFeed, Inc.", "short_name": "BuzzFeed, Inc.", "sector": "Communication Services", "industry": "Internet Content & Information", "country": "United States", "market_cap": 30495572, "float_shares": 20892221, "shares_outstanding": 35864575, "short_ratio": 5.01, "short_percent_of_float": 0.050300002, "shares_short": 1528928, "shares_short_prior": 1582619, "insider_percent_held": 0.33015, "institution_percent_held": 0.16472, "total_cash": 34292000, "total_debt": 82559000, "total_revenue": 184927008, "revenue_growth": -0.166, "earnings_growth": 0, "profit_margins": 0.00057, "gross_margins": 0.41612, "operating_margins": -0.0947, "debt_to_equity": 107.701, "current_ratio": 0.89, "book_value": 2.039, "price_to_book": 0.40196174, "operating_cashflow": -11574000, "free_cashflow": 20361250, "price": 0.8196, "52w_high": 2.68, "52w_low": 0.774, "avg_volume": 359561, "avg_volume_10d": 191280, "full_time_employees": 611, "audit_risk": 0, "overall_risk": 0}}